zinny_api/__init__.py
zinny_api/cli.py
zinny_api/config.py
zinny_api/_attic/routes/__init__.py
zinny_api/_attic/routes/errors.py
zinny_api/api/__init__.py
zinny_api/api/collections.py
zinny_api/api/ratings.py
zinny_api/api/screen_types.py
zinny_api/api/service.py
zinny_api/api/surveys.py
zinny_api/api/title_types.py
zinny_api/api/titles.py
zinny_api/api/weights.py
zinny_api/data/title_types/shared/title_types.json
zinny_api/data/titles/shared/titles_2024_sample.tsv
zinny_api/data/titles/shared/titles_default.json
zinny_api/data/titles/shared/titles_sample_file.tsv
zinny_api/db/__init__.py
zinny_api/db/db_init.py
zinny_api/db/db_schema.py
zinny_api/utils/__init__.py
zinny_api/utils/import_helpers/__init__.py
zinny_api/utils/import_helpers/common.py
zinny_api/utils/import_helpers/surveys.py
zinny_api/utils/import_helpers/title_types.py
zinny_api/utils/import_helpers/titles.py
zinny_api/utils/import_helpers/weights.py
zinny_api-1.0.19.dist-info/LICENSE
zinny_api-1.0.19.dist-info/METADATA
zinny_api-1.0.19.dist-info/WHEEL
zinny_api-1.0.19.dist-info/entry_points.txt
zinny_api-1.0.19.dist-info/top_level.txt
zinny_api-1.0.19.dist-info/RECORD
